[
  {
    "name": "A1",
    "meta": {
      "uses_haralick": true,
      "uses_haralick_differences": false,
      "uses_lbp": false,
      "uses_lbp_differences": false,
      "detail_level": "1-corpo"
    },
    "dataset_keys": [
      "haralick.full_body"
    ]
  },
  {
    "name": "A1D1",
    "meta": {
      "uses_haralick": true,
      "uses_haralick_differences": true,
      "uses_lbp": false,
      "uses_lbp_differences": false,
      "detail_level": "1-corpo"
    },
    "dataset_keys": [
      "haralick.full_body",
      "haralick.corpo_lado_diff"
    ]
  },
  {
    "name": "A1D2",
    "meta": {
      "uses_haralick": true,
      "uses_haralick_differences": true,
      "uses_lbp": false,
      "uses_lbp_differences": false,
      "detail_level": "1-corpo"
    },
    "dataset_keys": [
      "haralick.full_body",
      "haralick.corpo_lado_diff_squared"
    ]
  },
  {
    "name": "A2",
    "meta": {
      "uses_haralick": true,
      "uses_haralick_differences": false,
      "uses_lbp": false,
      "uses_lbp_differences": false,
      "detail_level": "2-lados-corpo"
    },
    "dataset_keys": [
      "haralick.corpo_lado_esq",
      "haralick.corpo_lado_dir"
    ]
  },
  {
    "name": "A2D1",
    "meta": {
      "uses_haralick": true,
      "uses_haralick_differences": true,
      "uses_lbp": false,
      "uses_lbp_differences": false,
      "detail_level": "2-lados-corpo"
    },
    "dataset_keys": [
      "haralick.corpo_lado_esq",
      "haralick.corpo_lado_dir",
      "haralick.corpo_lado_diff"
    ]
  },
  {
    "name": "A2D2",
    "meta": {
      "uses_haralick": true,
      "uses_haralick_differences": true,
      "uses_lbp": false,
      "uses_lbp_differences": false,
      "detail_level": "2-lados-corpo"
    },
    "dataset_keys": [
      "haralick.corpo_lado_esq",
      "haralick.corpo_lado_dir",
      "haralick.corpo_lado_diff_squared"
    ]
  },
  {
    "name": "A3",
    "meta": {
      "uses_haralick": true,
      "uses_haralick_differences": false,
      "uses_lbp": false,
      "uses_lbp_differences": false,
      "detail_level": "3-mamas"
    },
    "dataset_keys": [
      "haralick.quadrante_full_esq",
      "haralick.quadrante_full_dir"
    ]
  },
  {
    "name": "A3D1",
    "meta": {
      "uses_haralick": true,
      "uses_haralick_differences": true,
      "uses_lbp": false,
      "uses_lbp_differences": false,
      "detail_level": "3-mamas"
    },
    "dataset_keys": [
      "haralick.quadrante_full_esq",
      "haralick.quadrante_full_dir",
      "haralick.quadrante_full_diff"
    ]
  },
  {
    "name": "A3D2",
    "meta": {
      "uses_haralick": true,
      "uses_haralick_differences": true,
      "uses_lbp": false,
      "uses_lbp_differences": false,
      "detail_level": "3-mamas"
    },
    "dataset_keys": [
      "haralick.quadrante_full_esq",
      "haralick.quadrante_full_dir",
      "haralick.quadrante_full_diff_squared"
    ]
  },
  {
    "name": "A4",
    "meta": {
      "uses_haralick": true,
      "uses_haralick_differences": false,
      "uses_lbp": false,
      "uses_lbp_differences": false,
      "detail_level": "4-quadrantes"
    },
    "dataset_keys": [
      "haralick.quadrante_si_esq",
      "haralick.quadrante_si_dir",
      "haralick.quadrante_ie_esq",
      "haralick.quadrante_ie_dir",
      "haralick.quadrante_ii_esq",
      "haralick.quadrante_ii_dir",
      "haralick.quadrante_se_esq",
      "haralick.quadrante_se_dir"
    ]
  },
  {
    "name": "A4D1",
    "meta": {
      "uses_haralick": true,
      "uses_haralick_differences": true,
      "uses_lbp": false,
      "uses_lbp_differences": false,
      "detail_level": "4-quadrantes"
    },
    "dataset_keys": [
      "haralick.quadrante_si_esq",
      "haralick.quadrante_si_dir",
      "haralick.quadrante_ie_esq",
      "haralick.quadrante_ie_dir",
      "haralick.quadrante_ii_esq",
      "haralick.quadrante_ii_dir",
      "haralick.quadrante_se_esq",
      "haralick.quadrante_se_dir",
      "haralick.quadrante_si_diff",
      "haralick.quadrante_ie_diff",
      "haralick.quadrante_ii_diff",
      "haralick.quadrante_se_diff"
    ]
  },
  {
    "name": "A4D2",
    "meta": {
      "uses_haralick": true,
      "uses_haralick_differences": true,
      "uses_lbp": false,
      "uses_lbp_differences": false,
      "detail_level": "4-quadrantes"
    },
    "dataset_keys": [
      "haralick.quadrante_si_esq",
      "haralick.quadrante_si_dir",
      "haralick.quadrante_ie_esq",
      "haralick.quadrante_ie_dir",
      "haralick.quadrante_ii_esq",
      "haralick.quadrante_ii_dir",
      "haralick.quadrante_se_esq",
      "haralick.quadrante_se_dir",
      "haralick.quadrante_si_diff_squared",
      "haralick.quadrante_ie_diff_squared",
      "haralick.quadrante_ii_diff_squared",
      "haralick.quadrante_se_diff_squared"
    ]
  },
  {
    "name": "B2",
    "meta": {
      "uses_haralick": false,
      "uses_haralick_differences": false,
      "uses_lbp": true,
      "uses_lbp_differences": false,
      "detail_level": "2-lados-corpo"
    },
    "dataset_keys": [
      "lbp.corpo_lado_esq",
      "lbp.corpo_lado_dir"
    ]
  },
  {
    "name": "B2D1",
    "meta": {
      "uses_haralick": false,
      "uses_haralick_differences": false,
      "uses_lbp": true,
      "uses_lbp_differences": true,
      "detail_level": "2-lados-corpo"
    },
    "dataset_keys": [
      "lbp.corpo_lado_esq",
      "lbp.corpo_lado_dir",
      "lbp.corpo_lado_distances"
    ]
  },
  {
    "name": "B3",
    "meta": {
      "uses_haralick": false,
      "uses_haralick_differences": false,
      "uses_lbp": true,
      "uses_lbp_differences": false,
      "detail_level": "3-mamas"
    },
    "dataset_keys": [
      "lbp.mama_esq",
      "lbp.mama_dir"
    ]
  },
  {
    "name": "B3D1",
    "meta": {
      "uses_haralick": false,
      "uses_haralick_differences": false,
      "uses_lbp": true,
      "uses_lbp_differences": true,
      "detail_level": "3-mamas"
    },
    "dataset_keys": [
      "lbp.mama_esq",
      "lbp.mama_dir",
      "lbp.mama_distances"
    ]
  },
  {
    "name": "B4",
    "meta": {
      "uses_haralick": false,
      "uses_haralick_differences": false,
      "uses_lbp": true,
      "uses_lbp_differences": false,
      "detail_level": "4-quadrantes"
    },
    "dataset_keys": [
      "lbp.quadrante_si_esq",
      "lbp.quadrante_si_dir",
      "lbp.quadrante_ie_esq",
      "lbp.quadrante_ie_dir",
      "lbp.quadrante_ii_esq",
      "lbp.quadrante_ii_dir",
      "lbp.quadrante_se_esq",
      "lbp.quadrante_se_dir"
    ]
  },
  {
    "name": "B4D1",
    "meta": {
      "uses_haralick": false,
      "uses_haralick_differences": false,
      "uses_lbp": true,
      "uses_lbp_differences": true,
      "detail_level": "4-quadrantes"
    },
    "dataset_keys": [
      "lbp.quadrante_si_esq",
      "lbp.quadrante_si_dir",
      "lbp.quadrante_si_distances",
      "lbp.quadrante_ie_esq",
      "lbp.quadrante_ie_dir",
      "lbp.quadrante_ie_distances",
      "lbp.quadrante_ii_esq",
      "lbp.quadrante_ii_dir",
      "lbp.quadrante_ii_distances",
      "lbp.quadrante_se_esq",
      "lbp.quadrante_se_dir",
      "lbp.quadrante_se_distances"
    ]
  },
  {
    "name": "C1",
    "meta": {
      "uses_haralick": true,
      "uses_haralick_differences": false,
      "uses_lbp": true,
      "uses_lbp_differences": false,
      "detail_level": "1-corpo"
    },
    "dataset_keys": [
      "haralick.full_body",
      "lbp.corpo_lado_esq",
      "lbp.corpo_lado_dir"
    ]
  },
  {
    "name": "C1D",
    "meta": {
      "uses_haralick": true,
      "uses_haralick_differences": true,
      "uses_lbp": true,
      "uses_lbp_differences": true,
      "detail_level": "1-corpo"
    },
    "dataset_keys": [
      "haralick.full_body",
      "haralick.corpo_lado_diff",
      "lbp.corpo_lado_esq",
      "lbp.corpo_lado_dir",
      "lbp.corpo_lado_distances"
    ]
  },
  {
    "name": "C2",
    "meta": {
      "uses_haralick": true,
      "uses_haralick_differences": false,
      "uses_lbp": true,
      "uses_lbp_differences": false,
      "detail_level": "2-lados-corpo"
    },
    "dataset_keys": [
      "haralick.corpo_lado_esq",
      "haralick.corpo_lado_dir",
      "lbp.corpo_lado_esq",
      "lbp.corpo_lado_dir"
    ]
  },
  {
    "name": "C2D",
    "meta": {
      "uses_haralick": true,
      "uses_haralick_differences": true,
      "uses_lbp": true,
      "uses_lbp_differences": true,
      "detail_level": "2-lados-corpo"
    },
    "dataset_keys": [
      "haralick.corpo_lado_esq",
      "haralick.corpo_lado_dir",
      "haralick.corpo_lado_diff",
      "lbp.corpo_lado_esq",
      "lbp.corpo_lado_dir",
      "lbp.corpo_lado_distances"
    ]
  },
  {
    "name": "C3",
    "meta": {
      "uses_haralick": true,
      "uses_haralick_differences": false,
      "uses_lbp": true,
      "uses_lbp_differences": false,
      "detail_level": "3-mamas"
    },
    "dataset_keys": [
      "haralick.quadrante_full_esq",
      "haralick.quadrante_full_dir",
      "lbp.mama_esq",
      "lbp.mama_dir"
    ]
  },
  {
    "name": "C3D",
    "meta": {
      "uses_haralick": true,
      "uses_haralick_differences": true,
      "uses_lbp": true,
      "uses_lbp_differences": true,
      "detail_level": "3-mamas"
    },
    "dataset_keys": [
      "haralick.quadrante_full_esq",
      "haralick.quadrante_full_dir",
      "haralick.quadrante_full_diff",
      "lbp.mama_esq",
      "lbp.mama_dir",
      "lbp.mama_distances"
    ]
  },
  {
    "name": "C4",
    "meta": {
      "uses_haralick": true,
      "uses_haralick_differences": false,
      "uses_lbp": true,
      "uses_lbp_differences": false,
      "detail_level": "4-quadrantes"
    },
    "dataset_keys": [
      "haralick.quadrante_si_esq",
      "haralick.quadrante_si_dir",
      "haralick.quadrante_ie_esq",
      "haralick.quadrante_ie_dir",
      "haralick.quadrante_ii_esq",
      "haralick.quadrante_ii_dir",
      "haralick.quadrante_se_esq",
      "haralick.quadrante_se_dir",
      "lbp.quadrante_si_esq",
      "lbp.quadrante_si_dir",
      "lbp.quadrante_ie_esq",
      "lbp.quadrante_ie_dir",
      "lbp.quadrante_ii_esq",
      "lbp.quadrante_ii_dir",
      "lbp.quadrante_se_esq",
      "lbp.quadrante_se_dir"
    ]
  },
  {
    "name": "C4D",
    "meta": {
      "uses_haralick": true,
      "uses_haralick_differences": true,
      "uses_lbp": true,
      "uses_lbp_differences": true,
      "detail_level": "4-quadrantes"
    },
    "dataset_keys": [
      "haralick.quadrante_si_esq",
      "haralick.quadrante_si_dir",
      "haralick.quadrante_ie_esq",
      "haralick.quadrante_ie_dir",
      "haralick.quadrante_ii_esq",
      "haralick.quadrante_ii_dir",
      "haralick.quadrante_se_esq",
      "haralick.quadrante_se_dir",
      "haralick.quadrante_si_diff",
      "haralick.quadrante_ie_diff",
      "haralick.quadrante_ii_diff",
      "haralick.quadrante_se_diff",
      "lbp.quadrante_si_esq",
      "lbp.quadrante_si_dir",
      "lbp.quadrante_si_distances",
      "lbp.quadrante_ie_esq",
      "lbp.quadrante_ie_dir",
      "lbp.quadrante_ie_distances",
      "lbp.quadrante_ii_esq",
      "lbp.quadrante_ii_dir",
      "lbp.quadrante_ii_distances",
      "lbp.quadrante_se_esq",
      "lbp.quadrante_se_dir",
      "lbp.quadrante_se_distances"
    ]
  }
]